<?xml version="1.0" encoding="UTF-8"?><record_update table="sys_relationship">
    <sys_relationship action="DELETE">
        <advanced>false</advanced>
        <apply_to/>
        <basic_apply_to>sys_user</basic_apply_to>
        <basic_query_from>x_568222_fsm_ask_a_question</basic_query_from>
        <insert_callback/>
        <name>Create a Task </name>
        <query_from/>
        <query_with><![CDATA[current.addQuery('assigned_to', parent.sys_id);]]></query_with>
        <reference_field>assigned_to</reference_field>
        <related_list/>
        <simple_reference>true</simple_reference>
        <sys_class_name>sys_relationship</sys_class_name>
        <sys_created_by>admin</sys_created_by>
        <sys_created_on>2021-02-05 13:29:30</sys_created_on>
        <sys_id>619e934bdb0e2010e420b08039961960</sys_id>
        <sys_mod_count>2</sys_mod_count>
        <sys_name>Create a Task </sys_name>
        <sys_package display_value="Finance Serivce Management" source="x_568222_fsm">5c67a5f1db422010e420b080399619ce</sys_package>
        <sys_policy/>
        <sys_scope display_value="Finance Serivce Management">5c67a5f1db422010e420b080399619ce</sys_scope>
        <sys_update_name>sys_relationship_619e934bdb0e2010e420b08039961960</sys_update_name>
        <sys_updated_by>admin</sys_updated_by>
        <sys_updated_on>2021-02-05 13:43:35</sys_updated_on>
    </sys_relationship>
    <sys_translated_text action="DELETE" query="documentkey=619e934bdb0e2010e420b08039961960"/>
    <sys_update_version action="INSERT_OR_UPDATE">
        <action>DELETE</action>
        <application display_value="Finance Serivce Management">5c67a5f1db422010e420b080399619ce</application>
        <file_path/>
        <instance_id>1c6f5076dbf037002f68c597059619c3</instance_id>
        <instance_name>dev81591</instance_name>
        <name>sys_relationship_619e934bdb0e2010e420b08039961960</name>
        <payload>&lt;?xml version="1.0" encoding="UTF-8"?&gt;&lt;record_update table="sys_relationship"&gt;&lt;sys_relationship action="INSERT_OR_UPDATE"&gt;&lt;advanced&gt;false&lt;/advanced&gt;&lt;apply_to/&gt;&lt;basic_apply_to&gt;sys_user&lt;/basic_apply_to&gt;&lt;basic_query_from&gt;x_568222_fsm_ask_a_question&lt;/basic_query_from&gt;&lt;insert_callback/&gt;&lt;name&gt;Create a Task &lt;/name&gt;&lt;query_from/&gt;&lt;query_with&gt;&lt;![CDATA[current.addQuery('assigned_to', parent.sys_id);]]&gt;&lt;/query_with&gt;&lt;reference_field&gt;assigned_to&lt;/reference_field&gt;&lt;related_list/&gt;&lt;simple_reference&gt;true&lt;/simple_reference&gt;&lt;sys_class_name&gt;sys_relationship&lt;/sys_class_name&gt;&lt;sys_created_by&gt;admin&lt;/sys_created_by&gt;&lt;sys_created_on&gt;2021-02-05 13:29:30&lt;/sys_created_on&gt;&lt;sys_id&gt;619e934bdb0e2010e420b08039961960&lt;/sys_id&gt;&lt;sys_mod_count&gt;2&lt;/sys_mod_count&gt;&lt;sys_name&gt;Create a Task &lt;/sys_name&gt;&lt;sys_package display_value="Finance Serivce Management" source="x_568222_fsm"&gt;5c67a5f1db422010e420b080399619ce&lt;/sys_package&gt;&lt;sys_policy/&gt;&lt;sys_scope display_value="Finance Serivce Management"&gt;5c67a5f1db422010e420b080399619ce&lt;/sys_scope&gt;&lt;sys_update_name&gt;sys_relationship_619e934bdb0e2010e420b08039961960&lt;/sys_update_name&gt;&lt;sys_updated_by&gt;admin&lt;/sys_updated_by&gt;&lt;sys_updated_on&gt;2021-02-05 13:43:35&lt;/sys_updated_on&gt;&lt;/sys_relationship&gt;&lt;sys_translated_text action="delete_multiple" query="documentkey=619e934bdb0e2010e420b08039961960"/&gt;&lt;/record_update&gt;</payload>
        <payload_hash>1681494336</payload_hash>
        <record_name>Create a Task </record_name>
        <reverted_from/>
        <source>ed28adf1db422010e420b080399619c1</source>
        <source_table>sys_update_set</source_table>
        <state>previous</state>
        <sys_created_by>admin</sys_created_by>
        <sys_created_on>2021-02-05 13:43:35</sys_created_on>
        <sys_id>02d3670fdb0e2010e420b080399619bc</sys_id>
        <sys_mod_count>0</sys_mod_count>
        <sys_recorded_at>177726f09040000001</sys_recorded_at>
        <sys_updated_by>admin</sys_updated_by>
        <sys_updated_on>2021-02-05 13:43:35</sys_updated_on>
        <type>Relationship</type>
        <update_guid>8ad3670f910e201092dc702ddf0059bb</update_guid>
        <update_guid_history>8ad3670f910e201092dc702ddf0059bb:1681494336,5d93670f2e0e2010c931122d1d8163dc:-801119883,eb906f4b480e201058d0b8df3528d3cb:2141340963</update_guid_history>
    </sys_update_version>
    <sys_metadata_delete action="INSERT_OR_UPDATE">
        <sys_audit_delete/>
        <sys_class_name>sys_metadata_delete</sys_class_name>
        <sys_created_by>admin</sys_created_by>
        <sys_created_on>2021-02-05 13:45:49</sys_created_on>
        <sys_db_object display_value="" name="sys_relationship">sys_relationship</sys_db_object>
        <sys_id>09ea2f45806042e084e073cece6ef900</sys_id>
        <sys_metadata>619e934bdb0e2010e420b08039961960</sys_metadata>
        <sys_mod_count>0</sys_mod_count>
        <sys_name>Create a Task </sys_name>
        <sys_package display_value="Finance Serivce Management" source="x_568222_fsm">5c67a5f1db422010e420b080399619ce</sys_package>
        <sys_parent display_value="Sys User">8540bb00c923101091f9f064648327e1</sys_parent>
        <sys_policy/>
        <sys_scope display_value="Finance Serivce Management">5c67a5f1db422010e420b080399619ce</sys_scope>
        <sys_scope_delete display_value="">9526c521070b416c9ed74824404c3644</sys_scope_delete>
        <sys_update_name>sys_relationship_619e934bdb0e2010e420b08039961960</sys_update_name>
        <sys_update_version display_value="sys_relationship_619e934bdb0e2010e420b08039961960">02d3670fdb0e2010e420b080399619bc</sys_update_version>
        <sys_updated_by>admin</sys_updated_by>
        <sys_updated_on>2021-02-05 13:45:49</sys_updated_on>
    </sys_metadata_delete>
</record_update>
